README.md
setup.py
sample_app/__init__.py
sample_app/sample_app.py
sample_app/package_one/__init__.py
sample_app/package_one/pack_one.py
sample_app/package_two/__init__.py
sample_app/package_two/pack_two.py
satotimes.egg-info/PKG-INFO
satotimes.egg-info/SOURCES.txt
satotimes.egg-info/dependency_links.txt
satotimes.egg-info/top_level.txt
test/__init__.py
test/test_pack_one.py
test/test_pack_two.py