Metadata-Version: 2.1
Name: satotimes
Version: 0.0.1
Summary: A small example package
Home-page: https://bitbucket.org/avilay/sample-app
Author: sato
Author-email: satokarashi@gmail.com
License: UNKNOWN
Platform: UNKNOWN
Classifier: Programming Language :: Python :: 3
Classifier: License :: OSI Approved :: MIT License
Classifier: Operating System :: OS Independent
